{
    "app": {
        "name": "Mussifly V4.0",
        "tagline": "Feel The Music, Beyond Limits."
    },
    "downloads": {
        "arm64": "https://www.mediafire.com/file/0hvec0htfkbdt6e/MussiFly_v4.0__64bit.apk/file",
        "arm32": "https://www.mediafire.com/file/s59hgh1ya3c6e0d/MussiFly_v4.0__32bit.apk/file"
    },
    "stats": {
        "downloads": "500+",
        "rating": "4.9/5",
        "songs": "Unlimited"
    },
    "social": {
        "twitter": "https://twitter.com/musifly",
        "instagram": "https://instagram.com/musifly.in",
        "facebook": "https://facebook.com/musifly",
        "github": "https://t.me/sktech_000",
        "telegram": "https://t.me/mussifly"
    },
    "footer": {
        "description": "The ultimate AI-powered music player for Android. Experience music like never before with advanced audio engineering and stunning design.",
        "menus": {
            "product": {
                "features": "#features",
                "download": "#download",
                "premium": "#premium",
                "changelog": "#changelog"
            },
            "legal": {
                "privacy": "#privacy",
                "terms": "#terms",
                "cookies": "#cookies",
                "contact": "#contact"
            }
        }
    },
    "screenshots": {
        "left": "/screenshot-left.jpg",
        "right": "/screenshot-right.jpg",
        "center": "/screenshot-center.jpg"
    }
}
